furiosa_native_postprocess-0.10.0.dist-info/METADATA
furiosa_native_postprocess-0.10.0.dist-info/WHEEL
furiosa_native_postprocess/__init__.py
furiosa_native_postprocess/furiosa_native_postprocess.cpython-311-x86_64-linux-gnu.so
furiosa_native_postprocess-0.10.0.dist-info/RECORD
