Metadata-Version: 2.1
Name: furiosa-native-postprocess
Version: 0.10.0
